xuerui_stat/__init__.py
xuerui_stat/analysis/__init__.py
xuerui_stat/analysis/factor_analysis.py
xuerui_stat/analysis/random_forest/__init__.py
xuerui_stat/analysis/random_forest/decision_tree.py
xuerui_stat/analysis/random_forest/plot_tree.py
xuerui_stat/analysis/random_forest/preprocessing.py
xuerui_stat/analysis/random_forest/random_forest.py
xuerui_stat/datatool/__init__.py
xuerui_stat/datatool/basic_func.py
xuerui_stat/datatool/data_directory.py
xuerui_stat/datatool/data_manager.py
xuerui_stat/visualisation/__init__.py
xuerui_stat/visualisation/settings.py
xuerui_stat/visualisation/visual_data.py
xuerui_stat-0.0.8.dist-info/LICENSE
xuerui_stat-0.0.8.dist-info/METADATA
xuerui_stat-0.0.8.dist-info/WHEEL
xuerui_stat-0.0.8.dist-info/top_level.txt
xuerui_stat-0.0.8.dist-info/RECORD
