Metadata-Version: 2.1
Name: xuerui-stat
Version: 0.0.8
Summary: A statistical package to manage and analyse data
Home-page: https://github.com/Xuerui-Yang/xuerui-stat
Author: Xuerui Yang
Author-email: xuerui-yang@outlook.com
License: UNKNOWN
Platform: UNKNOWN
Classifier: Programming Language :: Python :: 3
Classifier: License :: OSI Approved :: MIT License
Classifier: Operating System :: OS Independent
Requires-Python: >=3.7
